PythonYufaJichuKuaisuRumen/README.md
PythonYufaJichuKuaisuRumen/__init__.py
PythonYufaJichuKuaisuRumen/__main__.py
PythonYufaJichuKuaisuRumen/file.epub
PythonYufaJichuKuaisuRumen/index.html
PythonYufaJichuKuaisuRumen/css/__init__.py
PythonYufaJichuKuaisuRumen/css/annotations.css
PythonYufaJichuKuaisuRumen/css/main.css
PythonYufaJichuKuaisuRumen/css/normalize.css
PythonYufaJichuKuaisuRumen/css/popup.css
PythonYufaJichuKuaisuRumen/font/__init__.py
PythonYufaJichuKuaisuRumen/font/fontello.eot
PythonYufaJichuKuaisuRumen/font/fontello.svg
PythonYufaJichuKuaisuRumen/font/fontello.ttf
PythonYufaJichuKuaisuRumen/font/fontello.woff
PythonYufaJichuKuaisuRumen/img/__init__.py
PythonYufaJichuKuaisuRumen/img/annotator-glyph-sprite.png
PythonYufaJichuKuaisuRumen/img/annotator-icon-sprite.png
PythonYufaJichuKuaisuRumen/img/apple-touch-icon.png
PythonYufaJichuKuaisuRumen/img/cancelfullscreen.png
PythonYufaJichuKuaisuRumen/img/close.png
PythonYufaJichuKuaisuRumen/img/fullscreen.png
PythonYufaJichuKuaisuRumen/img/loader.gif
PythonYufaJichuKuaisuRumen/img/menu-icon.png
PythonYufaJichuKuaisuRumen/img/save.png
PythonYufaJichuKuaisuRumen/img/saved.png
PythonYufaJichuKuaisuRumen/img/settings-s.png
PythonYufaJichuKuaisuRumen/img/settings.png
PythonYufaJichuKuaisuRumen/img/star.png
PythonYufaJichuKuaisuRumen/js/__init__.py
PythonYufaJichuKuaisuRumen/js/epub.js
PythonYufaJichuKuaisuRumen/js/epub.min.js
PythonYufaJichuKuaisuRumen/js/epub.min.map
PythonYufaJichuKuaisuRumen/js/hooks.min.js
PythonYufaJichuKuaisuRumen/js/hooks.min.map
PythonYufaJichuKuaisuRumen/js/reader.js
PythonYufaJichuKuaisuRumen/js/reader.js.map
PythonYufaJichuKuaisuRumen/js/reader.min.js
PythonYufaJichuKuaisuRumen/js/reader.min.map
PythonYufaJichuKuaisuRumen/js/hooks/__init__.py
PythonYufaJichuKuaisuRumen/js/hooks/extensions/__init__.py
PythonYufaJichuKuaisuRumen/js/hooks/extensions/highlight.js
PythonYufaJichuKuaisuRumen/js/libs/__init__.py
PythonYufaJichuKuaisuRumen/js/libs/jquery.min.js
python_yufa_jichu_kuaisu_rumen-2024.3.5.0.dist-info/METADATA
python_yufa_jichu_kuaisu_rumen-2024.3.5.0.dist-info/WHEEL
python_yufa_jichu_kuaisu_rumen-2024.3.5.0.dist-info/entry_points.txt
python_yufa_jichu_kuaisu_rumen-2024.3.5.0.dist-info/top_level.txt
python_yufa_jichu_kuaisu_rumen-2024.3.5.0.dist-info/RECORD
